[
    {
        "id": 1,
        "name": "Palmer",
        "lastname": "Gibson",
        "courseId": 72
    },
    {
        "id": 2,
        "name": "Mollie",
        "lastname": "Sawyer",
        "courseId": 62
    },
    {
        "id": 3,
        "name": "Daria",
        "lastname": "Peterson",
        "courseId": 68
    },
    {
        "id": 4,
        "name": "Noah",
        "lastname": "Curtis",
        "courseId": 40
    },
    {
        "id": 5,
        "name": "Brennan",
        "lastname": "Nash",
        "courseId": 4
    },
    {
        "id": 6,
        "name": "Dorian",
        "lastname": "Lindsey",
        "courseId": 36
    },
    {
        "id": 7,
        "name": "Rafael",
        "lastname": "Montoya",
        "courseId": 7
    },
    {
        "id": 8,
        "name": "Hoyt",
        "lastname": "Pace",
        "courseId": 35
    },
    {
        "id": 9,
        "name": "Phelan",
        "lastname": "Mclean",
        "courseId": 91
    },
    {
        "id": 10,
        "name": "Ahmed",
        "lastname": "Mack",
        "courseId": 86
    },
    {
        "id": 11,
        "name": "Kenneth",
        "lastname": "Dennis",
        "courseId": 87
    },
    {
        "id": 12,
        "name": "Eric",
        "lastname": "Moody",
        "courseId": 10
    },
    {
        "id": 13,
        "name": "Hu",
        "lastname": "Wade",
        "courseId": 81
    },
    {
        "id": 14,
        "name": "Jerry",
        "lastname": "Hawkins",
        "courseId": 11
    },
    {
        "id": 15,
        "name": "Macaulay",
        "lastname": "Warner",
        "courseId": 7
    },
    {
        "id": 16,
        "name": "Cheyenne",
        "lastname": "Pruitt",
        "courseId": 65
    },
    {
        "id": 17,
        "name": "Blake",
        "lastname": "Shaw",
        "courseId": 64
    },
    {
        "id": 18,
        "name": "Stuart",
        "lastname": "Rice",
        "courseId": 67
    },
    {
        "id": 19,
        "name": "Ferdinand",
        "lastname": "Camacho",
        "courseId": 57
    },
    {
        "id": 20,
        "name": "Eden",
        "lastname": "Travis",
        "courseId": 58
    },
    {
        "id": 21,
        "name": "Kirk",
        "lastname": "Gregory",
        "courseId": 33
    },
    {
        "id": 22,
        "name": "Mallory",
        "lastname": "Oliver",
        "courseId": 20
    },
    {
        "id": 23,
        "name": "Fritz",
        "lastname": "Sexton",
        "courseId": 62
    },
    {
        "id": 24,
        "name": "Stacey",
        "lastname": "Mitchell",
        "courseId": 63
    },
    {
        "id": 25,
        "name": "Jolie",
        "lastname": "Wiggins",
        "courseId": 30
    },
    {
        "id": 26,
        "name": "Nomlanga",
        "lastname": "Wise",
        "courseId": 82
    },
    {
        "id": 27,
        "name": "Fulton",
        "lastname": "Barnes",
        "courseId": 47
    },
    {
        "id": 28,
        "name": "Len",
        "lastname": "Odom",
        "courseId": 14
    },
    {
        "id": 29,
        "name": "Hermione",
        "lastname": "Cobb",
        "courseId": 100
    },
    {
        "id": 30,
        "name": "Malcolm",
        "lastname": "Olsen",
        "courseId": 8
    },
    {
        "id": 31,
        "name": "Rose",
        "lastname": "Norris",
        "courseId": 84
    },
    {
        "id": 32,
        "name": "Eden",
        "lastname": "Bender",
        "courseId": 85
    },
    {
        "id": 33,
        "name": "Shaine",
        "lastname": "Chandler",
        "courseId": 3
    },
    {
        "id": 34,
        "name": "Inez",
        "lastname": "Combs",
        "courseId": 10
    },
    {
        "id": 35,
        "name": "Jessamine",
        "lastname": "Bradshaw",
        "courseId": 20
    },
    {
        "id": 36,
        "name": "Neville",
        "lastname": "Valencia",
        "courseId": 75
    },
    {
        "id": 37,
        "name": "Hayes",
        "lastname": "Kim",
        "courseId": 1
    },
    {
        "id": 38,
        "name": "Leah",
        "lastname": "Mooney",
        "courseId": 30
    },
    {
        "id": 39,
        "name": "Piper",
        "lastname": "Henry",
        "courseId": 94
    },
    {
        "id": 40,
        "name": "Jarrod",
        "lastname": "Moody",
        "courseId": 60
    },
    {
        "id": 41,
        "name": "Addison",
        "lastname": "Rogers",
        "courseId": 4
    },
    {
        "id": 42,
        "name": "Desiree",
        "lastname": "House",
        "courseId": 90
    },
    {
        "id": 43,
        "name": "Leilani",
        "lastname": "Griffith",
        "courseId": 3
    },
    {
        "id": 44,
        "name": "Penelope",
        "lastname": "Simpson",
        "courseId": 2
    },
    {
        "id": 45,
        "name": "Bethany",
        "lastname": "Russell",
        "courseId": 21
    },
    {
        "id": 46,
        "name": "Zeph",
        "lastname": "Arnold",
        "courseId": 93
    },
    {
        "id": 47,
        "name": "Lamar",
        "lastname": "Steele",
        "courseId": 59
    },
    {
        "id": 48,
        "name": "Colby",
        "lastname": "West",
        "courseId": 74
    },
    {
        "id": 49,
        "name": "Charles",
        "lastname": "Ross",
        "courseId": 53
    },
    {
        "id": 50,
        "name": "Rhea",
        "lastname": "Drake",
        "courseId": 76
    },
    {
        "id": 51,
        "name": "Sarah",
        "lastname": "Becker",
        "courseId": 86
    },
    {
        "id": 52,
        "name": "Nash",
        "lastname": "Ballard",
        "courseId": 26
    },
    {
        "id": 53,
        "name": "Gray",
        "lastname": "Peterson",
        "courseId": 54
    },
    {
        "id": 54,
        "name": "Hilary",
        "lastname": "Durham",
        "courseId": 53
    },
    {
        "id": 55,
        "name": "Andrew",
        "lastname": "Hartman",
        "courseId": 75
    },
    {
        "id": 56,
        "name": "Seth",
        "lastname": "Parrish",
        "courseId": 24
    },
    {
        "id": 57,
        "name": "Francis",
        "lastname": "Medina",
        "courseId": 1
    },
    {
        "id": 58,
        "name": "Charde",
        "lastname": "Smith",
        "courseId": 33
    },
    {
        "id": 59,
        "name": "Medge",
        "lastname": "Marshall",
        "courseId": 2
    },
    {
        "id": 60,
        "name": "Dorian",
        "lastname": "Faulkner",
        "courseId": 24
    },
    {
        "id": 61,
        "name": "Lacota",
        "lastname": "Valentine",
        "courseId": 88
    },
    {
        "id": 62,
        "name": "Sasha",
        "lastname": "Hartman",
        "courseId": 80
    },
    {
        "id": 63,
        "name": "Dorothy",
        "lastname": "Francis",
        "courseId": 19
    },
    {
        "id": 64,
        "name": "Vivian",
        "lastname": "Bryan",
        "courseId": 22
    },
    {
        "id": 65,
        "name": "Jonah",
        "lastname": "Knowles",
        "courseId": 87
    },
    {
        "id": 66,
        "name": "Kuame",
        "lastname": "Bradford",
        "courseId": 25
    },
    {
        "id": 67,
        "name": "Neve",
        "lastname": "Richardson",
        "courseId": 47
    },
    {
        "id": 68,
        "name": "Hanae",
        "lastname": "Irwin",
        "courseId": 87
    },
    {
        "id": 69,
        "name": "Denton",
        "lastname": "Savage",
        "courseId": 53
    },
    {
        "id": 70,
        "name": "Jonah",
        "lastname": "Green",
        "courseId": 3
    },
    {
        "id": 71,
        "name": "Jerry",
        "lastname": "Butler",
        "courseId": 33
    },
    {
        "id": 72,
        "name": "Kareem",
        "lastname": "Parks",
        "courseId": 80
    },
    {
        "id": 73,
        "name": "Penelope",
        "lastname": "Fuentes",
        "courseId": 13
    },
    {
        "id": 74,
        "name": "Celeste",
        "lastname": "Larson",
        "courseId": 37
    },
    {
        "id": 75,
        "name": "Lunea",
        "lastname": "Berry",
        "courseId": 68
    },
    {
        "id": 76,
        "name": "Thaddeus",
        "lastname": "Brown",
        "courseId": 33
    },
    {
        "id": 77,
        "name": "Stewart",
        "lastname": "Manning",
        "courseId": 15
    },
    {
        "id": 78,
        "name": "Janna",
        "lastname": "Mack",
        "courseId": 90
    },
    {
        "id": 79,
        "name": "Ruby",
        "lastname": "Burt",
        "courseId": 33
    },
    {
        "id": 80,
        "name": "Oliver",
        "lastname": "Sutton",
        "courseId": 78
    },
    {
        "id": 81,
        "name": "Macey",
        "lastname": "Russell",
        "courseId": 76
    },
    {
        "id": 82,
        "name": "Reed",
        "lastname": "Michael",
        "courseId": 50
    },
    {
        "id": 83,
        "name": "Barry",
        "lastname": "Curtis",
        "courseId": 85
    },
    {
        "id": 84,
        "name": "Trevor",
        "lastname": "Reeves",
        "courseId": 80
    },
    {
        "id": 85,
        "name": "Thaddeus",
        "lastname": "Weeks",
        "courseId": 77
    },
    {
        "id": 86,
        "name": "Isadora",
        "lastname": "Galloway",
        "courseId": 20
    },
    {
        "id": 87,
        "name": "Lacota",
        "lastname": "Giles",
        "courseId": 74
    },
    {
        "id": 88,
        "name": "Jorden",
        "lastname": "Nash",
        "courseId": 97
    },
    {
        "id": 89,
        "name": "Zeph",
        "lastname": "Velasquez",
        "courseId": 47
    },
    {
        "id": 90,
        "name": "Ryder",
        "lastname": "Montoya",
        "courseId": 42
    },
    {
        "id": 91,
        "name": "Micah",
        "lastname": "Wood",
        "courseId": 78
    },
    {
        "id": 92,
        "name": "Cole",
        "lastname": "Thornton",
        "courseId": 19
    },
    {
        "id": 93,
        "name": "Claudia",
        "lastname": "Gross",
        "courseId": 75
    },
    {
        "id": 94,
        "name": "Cailin",
        "lastname": "Malone",
        "courseId": 92
    },
    {
        "id": 95,
        "name": "Odysseus",
        "lastname": "Castillo",
        "courseId": 64
    },
    {
        "id": 96,
        "name": "Hope",
        "lastname": "Mcgowan",
        "courseId": 53
    },
    {
        "id": 97,
        "name": "Willa",
        "lastname": "Montgomery",
        "courseId": 12
    },
    {
        "id": 98,
        "name": "Cairo",
        "lastname": "Bartlett",
        "courseId": 55
    },
    {
        "id": 99,
        "name": "Ingrid",
        "lastname": "Carney",
        "courseId": 11
    },
    {
        "id": 100,
        "name": "Keely",
        "lastname": "Gill",
        "courseId": 48
    },
    {
        "id": 101,
        "name": "Dario",
        "lastname": "Flores",
        "courseId": 48
    }
]
